jupyter_rtc_automerge/__init__.py
jupyter_rtc_automerge/jupyter_rtc_automerge.cpython-39-darwin.so
jupyter_rtc_automerge/test_automerge.py
jupyter_rtc_automerge-0.1.1.dist-info/METADATA
jupyter_rtc_automerge-0.1.1.dist-info/WHEEL
jupyter_rtc_automerge-0.1.1.dist-info/top_level.txt
jupyter_rtc_automerge-0.1.1.dist-info/RECORD
