Metadata-Version: 2.1
Name: jupyter-rtc-automerge
Version: 0.1.1
Summary: The Jupyter RTC Python module using Automerge backend.
Home-page: https://github.com/jupyterlab/rtc
Author: Jupyter RTC
Author-email: UNKNOWN
License: UNKNOWN
Platform: UNKNOWN
